cloudwright_slack_webhook/__init__.py
cloudwright_slack_webhook-0.0.0.dist-info/METADATA
cloudwright_slack_webhook-0.0.0.dist-info/WHEEL
cloudwright_slack_webhook-0.0.0.dist-info/top_level.txt
cloudwright_slack_webhook-0.0.0.dist-info/RECORD
