Metadata-Version: 2.1
Name: cloudwright-slack-webhook
Version: 0.0.0
Summary: cloudwright_slack_webhook
Home-page: http://localhost
Author: cloudwright
Author-email: contact@rainshadow.cloud
License: UNKNOWN
Platform: UNKNOWN
Classifier: Programming Language :: Python :: 3
Classifier: Operating System :: OS Independent
